cmpparis/__init__.py
cmpparis/bod_config.py
cmpparis/bod_config_loader.py
cmpparis/bod_parser.py
cmpparis/bod_transformers.py
cmpparis/document_db_manager.py
cmpparis/error_handling.py
cmpparis/file.py
cmpparis/ftp.py
cmpparis/mssql.py
cmpparis/odbc.py
cmpparis/parameters_utils.py
cmpparis/quable_api.py
cmpparis/s3.py
cmpparis/ses_utils.py
cmpparis/sharepoint.py
cmpparis/sm_utils.py
cmpparis/sql_factory.py
cmpparis/sql_interface.py
cmpparis/utils.py
cmpparis-1.13.2.dist-info/licenses/LICENSE
cmpparis-1.13.2.dist-info/METADATA
cmpparis-1.13.2.dist-info/WHEEL
cmpparis-1.13.2.dist-info/top_level.txt
cmpparis-1.13.2.dist-info/RECORD
