Metadata-Version: 2.4
Name: cmpparis
Version: 1.13.2
Summary: Une bibliothèque pour CMP
Home-page: https://codecatalyst.aws/spaces/CMP/projects/Coding-Tools/source-repositories/python-cmpparis-lib/
Author: Sofiane Charrad | Hakim Lahiani
Author-email: s.charrad@cmp-paris.com | h.lahiani@cmp-paris.com
Classifier: Programming Language :: Python :: 3
Classifier: License :: OSI Approved :: MIT License
Classifier: Operating System :: OS Independent
Requires-Python: >=3.7
License-File: LICENSE
Requires-Dist: requests
Requires-Dist: paramiko
Requires-Dist: pyodbc
Requires-Dist: pymssql==2.3.4
Requires-Dist: Office365-REST-Python-Client
Requires-Dist: pymongo
Requires-Dist: pyyaml
Provides-Extra: file
Requires-Dist: pandas; extra == "file"
Requires-Dist: lxml; extra == "file"
Provides-Extra: test
Requires-Dist: moto; extra == "test"
Provides-Extra: dev
Requires-Dist: mkdocs>=1.5.0; extra == "dev"
Requires-Dist: mkdocs-material>=9.0.0; extra == "dev"
Requires-Dist: mkdocstrings[python]>=0.24.0; extra == "dev"
Requires-Dist: pytest>=7.0.0; extra == "dev"
Requires-Dist: pytest-cov>=4.0.0; extra == "dev"
Dynamic: author
Dynamic: author-email
Dynamic: classifier
Dynamic: description
Dynamic: description-content-type
Dynamic: home-page
Dynamic: license-file
Dynamic: provides-extra
Dynamic: requires-dist
Dynamic: requires-python
Dynamic: summary
